ghactions/__init__.py
ghactions/py.typed
ghactions-0.0.0.dist-info/LICENSE
ghactions-0.0.0.dist-info/METADATA
ghactions-0.0.0.dist-info/WHEEL
ghactions-0.0.0.dist-info/RECORD
